IMEM/IMEM.v
module Instruction_Memory(addr, inst);
input [31:0] addr;
output [31:0] inst;
reg [31:0] I_Mem [110:0];  
assign inst = I_Mem[addr];

always @(addr)
begin
        // R-type
        I_Mem[0] = 32'b0000000000000000000000000000000 ;       // no operation
        I_Mem[4] = 32'b0000000_11001_10000_000_01101_0110011;    // add x13, x16, x25
        I_Mem[8] = 32'b0100000_00011_01000_000_00101_0110011;     // sub x5, x8, x3
        I_Mem[12] = 32'b0000000_00011_00010_111_00001_0110011;    // and x1, x2, x3
        I_Mem[16] = 32'b0000000_00101_00011_110_00100_0110011;    // or x4, x3, x5
        I_Mem[20] = 32'b0000000_00101_00011_100_00100_0110011;    // xor x4, x3, x5
	I_Mem[24] = 32'b0000000_00101_00011_001_00100_0110011;    // sll x4, x3, x5
        I_Mem[28] = 32'b0000000_00101_00011_101_00100_0110011;    // srl x4, x3, x5
        I_Mem[32] = 32'b0100000_00010_00011_101_00101_0110011;    //sra x5, x3, x2
        I_Mem[36] = 32'b0000000_00010_00011_010_00101_0110011;    //slt x5, x3, x2 
        // I-type
        I_Mem[40]  = 32'b000000000010_10101_000_10110_0010011;     // addi x22, x21, 2
        I_Mem[44]  = 32'b000000000011_01000_110_01001_0010011;     // ori x9, x8, 3 
	I_Mem[48] = 32'b000000000100_01000_110_01001_0010011;     // xori x9, x8, 4
	I_Mem[52] = 32'b000000000101_00010_111_00001_0010011;     // andi x1, x2, 5
	I_Mem[56] = 32'b000000000110_00011_001_00100_0010011;    // slli x4, x3, 6
	I_Mem[60] = 32'b000000000111_00011_101_00100_0010011;    // srli x4, x3, 7 
	I_Mem[64] = 32'b000000001000_00011_101_00101_0010011;    //srai x5, x3, 8
	I_Mem[68] = 32'b000000001001_00011_010_00101_0010011;    //slti x5, x3, 9  
        // I-type
	I_Mem[72]=  32'b000000000101_00011_000_01001_0000011;     // lb x9, 5(x3)
	I_Mem[76] = 32'b000000000011_00011_001_01001_0000011;    // lh x9, 3(x3)
        I_Mem[80]= 32'b000000001111_00010_010_01000_0000011;    // lw x8, 15(x2) 
        // S-type
        I_Mem[84] =  32'b0000000_01111_00011_000_01000_0100011;     // sb x15, 8(x3), x3 = 12
	I_Mem[86] =  32'b0000000_01110_00110_001_01010_0100011;     // sh x14, 10(x6), x6 = 44
	I_Mem[90] = 32'b0000000_01110_00110_010_01100_0100011;     // sw x14, 12(x6), x6 = 44     
	//B-type    
	I_Mem[94] = 32'b0_000000_01001_01001_000_0110_0_1100011;     // beq x9, x9, 12, (PC + 12 if x9 = x9 
	I_Mem[98] = 32'b0_000000_01001_01001_001_0111_0_1100011;     //bne x9, x9, 14,(PC + 14 if x9 != x9)
	// U-type
        I_Mem[102] =  32'b00000000000000101000_00011_0110111;     // lui x3, 40
        I_Mem[106] =  32'b0000000000000010100_00101_0010111;     // auipc x5, 20 (rd = PC + (imm << 12))
	// J-type
	I_Mem[110] = 32'b0_00000000_0_0000010100_00001_1101111;         // jal x1, 20

end

endmodule

IMEM/IMEM_tb.v
module Instruction_Memory_tb;

    reg [31:0] addr;    // Input address signal
    wire [31:0] inst;   // Output instruction signal
    
    // Instantiate the Instruction_Memory module
    Instruction_Memory uut (
        .addr(addr),
        .inst(inst)
    );
    
    // Initialize signals and create the stimulus
    initial begin
        // Initialize address to 0
        $dumpfile("instruction_memory_tb.vcd");   // Name of the VCD file
        $dumpvars(0, Instruction_Memory_tb);      // Dump all signals in this testbench module
	addr = 32'b0;
        
        // Apply test vectors (memory address range 0 to 110)
        #10 addr = 32'd0;    // Read from memory address 0
        #10 addr = 32'd4;    // Read from memory address 4
        #10 addr = 32'd8;    // Read from memory address 8
        #10 addr = 32'd12;   // Read from memory address 12
        #10 addr = 32'd16;   // Read from memory address 16
        #10 addr = 32'd20;   // Read from memory address 20
        #10 addr = 32'd24;   // Read from memory address 24
        #10 addr = 32'd28;   // Read from memory address 28
        #10 addr = 32'd32;   // Read from memory address 32
        #10 addr = 32'd36;   // Read from memory address 36
        #10 addr = 32'd40;   // Read from memory address 40
        #10 addr = 32'd44;   // Read from memory address 44
        #10 addr = 32'd48;   // Read from memory address 48
        #10 addr = 32'd52;   // Read from memory address 52
        #10 addr = 32'd56;   // Read from memory address 56
        #10 addr = 32'd60;   // Read from memory address 60
        #10 addr = 32'd64;   // Read from memory address 64
        #10 addr = 32'd68;   // Read from memory address 68
        #10 addr = 32'd72;   // Read from memory address 72
        #10 addr = 32'd76;   // Read from memory address 76
        #10 addr = 32'd80;   // Read from memory address 80
        #10 addr = 32'd84;   // Read from memory address 84
        #10 addr = 32'd86;   // Read from memory address 86
        #10 addr = 32'd90;   // Read from memory address 90
        #10 addr = 32'd94;   // Read from memory address 94
        #10 addr = 32'd98;   // Read from memory address 98
        #10 addr = 32'd102;  // Read from memory address 102
        #10 addr = 32'd106;  // Read from memory address 106
        #10 addr = 32'd110;  // Read from memory address 110

        // Finish simulation
        #10 $finish;
    end

    // Monitor the output instruction
    initial begin
        $monitor("At time %t, addr = %d, inst = %h", $time, addr, inst);
    end

endmodule

instruction_memory_tb.vcd
$date
	Wed Apr 16 18:53:42 2025
$end
$version
	Icarus Verilog
$end
$timescale
	1s
$end
$scope module Instruction_Memory_tb $end
$var wire 32 ! inst [31:0] $end
$var reg 32 " addr [31:0] $end
$scope module uut $end
$var wire 32 # addr [31:0] $end
$var wire 32 $ inst [31:0] $end
$upscope $end
$upscope $end
$enddefinitions $end
#0
$dumpvars
b0 $
b0 #
b0 "
b0 !
$end
#20
b1100110000000011010110011 !
b1100110000000011010110011 $
b100 "
b100 #
#30
b1000000001101000000001010110011 !
b1000000001101000000001010110011 $
b1000 "
b1000 #
#40
b1100010111000010110011 !
b1100010111000010110011 $
b1100 "
b1100 #
#50
b10100011110001000110011 !
b10100011110001000110011 $
b10000 "
b10000 #
#60
b10100011100001000110011 !
b10100011100001000110011 $
b10100 "
b10100 #
#70
b10100011001001000110011 !
b10100011001001000110011 $
b11000 "
b11000 #
#80
b10100011101001000110011 !
b10100011101001000110011 $
b11100 "
b11100 #
#90
b1000000001000011101001010110011 !
b1000000001000011101001010110011 $
b100000 "
b100000 #
#100
b1000011010001010110011 !
b1000011010001010110011 $
b100100 "
b100100 #
#110
b1010101000101100010011 !
b1010101000101100010011 $
b101000 "
b101000 #
#120
b1101000110010010010011 !
b1101000110010010010011 $
b101100 "
b101100 #
#130
b10001000110010010010011 !
b10001000110010010010011 $
b110000 "
b110000 #
#140
b10100010111000010010011 !
b10100010111000010010011 $
b110100 "
b110100 #
#150
b11000011001001000010011 !
b11000011001001000010011 $
b111000 "
b111000 #
#160
b11100011101001000010011 !
b11100011101001000010011 $
b111100 "
b111100 #
#170
b100000011101001010010011 !
b100000011101001010010011 $
b1000000 "
b1000000 #
#180
b100100011010001010010011 !
b100100011010001010010011 $
b1000100 "
b1000100 #
#190
b10100011000010010000011 !
b10100011000010010000011 $
b1001000 "
b1001000 #
#200
b1100011001010010000011 !
b1100011001010010000011 $
b1001100 "
b1001100 #
#210
b111100010010010000000011 !
b111100010010010000000011 $
b1010000 "
b1010000 #
#220
b111100011000010000100011 !
b111100011000010000100011 $
b1010100 "
b1010100 #
#230
b111000110001010100100011 !
b111000110001010100100011 $
b1010110 "
b1010110 #
#240
b111000110010011000100011 !
b111000110010011000100011 $
b1011010 "
b1011010 #
#250
b100101001000011001100011 !
b100101001000011001100011 $
b1011110 "
b1011110 #
#260
b100101001001011101100011 !
b100101001001011101100011 $
b1100010 "
b1100010 #
#270
b101000000110110111 !
b101000000110110111 $
b1100110 "
b1100110 #
#280
b10100001010010111 !
b10100001010010111 $
b1101010 "
b1101010 #
#290
b10100000011101111 !
b10100000011101111 $
b1101110 "
b1101110 #
