DMEM/DMEM.v
//-----------------------------------------------------------------
//                      RISC-V Core Single Cycle Processor
//                                CA Lab
//-----------------------------------------------------------------
// Data_Memory

module Data_Memory(clk, rst_n, MemRW, addr, DataW, DataR);
    input clk, rst_n, MemRW;
    input [31:0] addr, DataW;
    output [31:0] DataR;

    integer k;
    reg [31:0] D_Mem [63:0];

    always @(posedge clk) begin
	D_Mem[17] <= 56;
	D_Mem[15] <= 65;
    end

    always @(posedge clk or negedge rst_n) begin
        if (!rst_n) begin
            for (k = 0; k < 64; k = k + 1) begin
                D_Mem[k] <= 32'b00;
            end
        end
        else if (!MemRW) begin //MemRW =0 => store the DataW 
            D_Mem[addr] <= DataW;
        end
    end

    assign DataW = ( MemRW ) ? D_Mem[addr] : 32'b0; //MemRW =1 => use DMEM , MEMRW=0 not using DMEM

endmodule

DMEM/DMEM_tb.v
module Data_Memory_tb;

    // Declare inputs to the DUT (Device Under Test)
    reg clk;
    reg rst_n;
    reg MemRW;
    reg [31:0] addr;
    reg [31:0] DataW;
    
    // Declare output of the DUT
    wire [31:0] DataR;
    
    // Instantiate the Data_Memory module
    Data_Memory uut (
        .clk(clk),
        .rst_n(rst_n),
        .MemRW(MemRW),
        .addr(addr),
        .DataW(DataW),
        .DataR(DataR)
    );
    
    // Clock Generation
    always begin
        #5 clk = ~clk; // Clock with 10 time unit period
    end
    
    // Initializing the signals and applying test vectors
    initial begin
        // Create a VCD file for waveform output
        $dumpfile("data_memory_tb.vcd");   // Name of the VCD file
        $dumpvars(0, Data_Memory_tb);      // Dump all signals in this testbench module
        
        // Initialize signals
        clk = 0;
        rst_n = 0;
        MemRW = 0;
        addr = 32'b0;
        DataW = 32'b0;
        
        // Apply reset
        #10 rst_n = 1; // Release reset after 10 time units
        
        // Test 1: Write data to address 17 (initial value should be 56)
        #10 MemRW = 0; addr = 32'd17; DataW = 32'd100; // Write 100 to address 17
        #10 MemRW = 1; addr = 32'd17; // Read from address 17 (should be 100)
        
        // Test 2: Write data to address 15 (initial value should be 65)
        #10 MemRW = 0; addr = 32'd15; DataW = 32'd200; // Write 200 to address 15
        #10 MemRW = 1; addr = 32'd15; // Read from address 15 (should be 200)
        
        // Test 3: Write to other address (e.g., address 10)
        #10 MemRW = 0; addr = 32'd10; DataW = 32'd300; // Write 300 to address 10
        #10 MemRW = 1; addr = 32'd10; // Read from address 10 (should be 300)
        
        // Test 4: Reset the memory and check data
        #10 rst_n = 0; // Apply reset
        #10 rst_n = 1; // Release reset
        #10 MemRW = 1; addr = 32'd10; // Read from address 10 (should be 0 after reset)
        
        // Test 5: Write and read at different addresses
        #10 MemRW = 0; addr = 32'd5; DataW = 32'd555; // Write 555 to address 5
        #10 MemRW = 1; addr = 32'd5; // Read from address 5 (should be 555)
        
        #10 MemRW = 0; addr = 32'd8; DataW = 32'd888; // Write 888 to address 8
        #10 MemRW = 1; addr = 32'd8; // Read from address 8 (should be 888)
        
        // Finish simulation
        #10 $finish;
    end

    // Monitor the output values
    initial begin
        $monitor("Time = %t, MemRW = %b, Addr = %d, DataW = %d, DataR = %d", 
                 $time, MemRW, addr, DataW, DataR);
    end

endmodule

DMEM/data_memory_tb.vcd
$date
	Wed Apr 16 19:50:40 2025
$end
$version
	Icarus Verilog
$end
$timescale
	1s
$end
$scope module Data_Memory_tb $end
$var wire 32 ! DataR [31:0] $end
$var reg 32 " DataW [31:0] $end
$var reg 1 # MemRW $end
$var reg 32 $ addr [31:0] $end
$var reg 1 % clk $end
$var reg 1 & rst_n $end
$scope module uut $end
$var wire 32 ' DataW [31:0] $end
$var wire 1 # MemRW $end
$var wire 32 ( addr [31:0] $end
$var wire 1 % clk $end
$var wire 1 & rst_n $end
$var reg 32 ) DataR [31:0] $end
$var integer 32 * k [31:0] $end
$upscope $end
$upscope $end
$enddefinitions $end
#0
$dumpvars
b1000000 *
b0 )
b0 (
b0 '
0&
0%
b0 $
0#
b0 "
b0 !
$end
#5
b1000000 *
1%
#10
0%
1&
#15
1%
#20
0%
b1100100 "
b1100100 '
b10001 $
b10001 (
#25
1%
#30
b1100100 !
b1100100 )
0%
1#
#35
b111000 !
b111000 )
1%
#40
b0 !
b0 )
0%
b11001000 "
b11001000 '
b1111 $
b1111 (
0#
#45
1%
#50
b11001000 !
b11001000 )
0%
1#
#55
b1000001 !
b1000001 )
1%
#60
b0 !
b0 )
0%
b100101100 "
b100101100 '
b1010 $
b1010 (
0#
#65
1%
#70
b100101100 !
b100101100 )
0%
1#
#75
1%
#80
b0 !
b0 )
b1000000 *
0%
0&
#85
b1000000 *
1%
#90
0%
1&
#95
1%
#100
0%
#105
1%
#110
0%
b1000101011 "
b1000101011 '
b101 $
b101 (
0#
#115
1%
#120
b1000101011 !
b1000101011 )
0%
1#
#125
1%
#130
b0 !
b0 )
0%
b1101111000 "
b1101111000 '
b1000 $
b1000 (
0#
#135
1%
#140
b1101111000 !
b1101111000 )
0%
1#
